ownerrez_wrapper/__init__.py
ownerrez_wrapper/api.py
ownerrez_wrapper/cli.py
ownerrez_wrapper/constants.py
ownerrez_wrapper/exceptions.py
ownerrez_wrapper/model.py
ownerrez_wrapper/restAdapter.py
tests/__init__.py
tests/test_api.py
ownerrez_wrapper-0.2.0.dist-info/LICENSE
ownerrez_wrapper-0.2.0.dist-info/METADATA
ownerrez_wrapper-0.2.0.dist-info/WHEEL
ownerrez_wrapper-0.2.0.dist-info/entry_points.txt
ownerrez_wrapper-0.2.0.dist-info/top_level.txt
ownerrez_wrapper-0.2.0.dist-info/RECORD
